pyqt_code_editor/__init__.py
pyqt_code_editor/_settings.py
pyqt_code_editor/app.py
pyqt_code_editor/environment_manager.py
pyqt_code_editor/sigmund-analyst.png
pyqt_code_editor/signal_router.py
pyqt_code_editor/themes.py
pyqt_code_editor/watchdog.py
pyqt_code_editor/code_editors/__init__.py
pyqt_code_editor/code_editors/code_editors.py
pyqt_code_editor/code_editors/languages/__init__.py
pyqt_code_editor/code_editors/languages/generic.py
pyqt_code_editor/code_editors/languages/javascript.py
pyqt_code_editor/code_editors/languages/markdown.py
pyqt_code_editor/code_editors/languages/python.py
pyqt_code_editor/code_editors/languages/text.py
pyqt_code_editor/components/__init__.py
pyqt_code_editor/components/editor_panel.py
pyqt_code_editor/components/find_in_files.py
pyqt_code_editor/components/jupyter_console.py
pyqt_code_editor/components/project_explorer.py
pyqt_code_editor/components/settings_panel.py
pyqt_code_editor/components/workspace_explorer.py
pyqt_code_editor/components/sigmund/__init__.py
pyqt_code_editor/components/sigmund/confirm_run_code_dialog.py
pyqt_code_editor/components/sigmund/editor_workspace.py
pyqt_code_editor/components/sigmund/sigmund.py
pyqt_code_editor/components/sigmund/sigmund_analyst_chat_widget.py
pyqt_code_editor/components/sigmund/sigmund_analyst_widget.py
pyqt_code_editor/mixins/__init__.py
pyqt_code_editor/mixins/auto_indent.py
pyqt_code_editor/mixins/auto_pair.py
pyqt_code_editor/mixins/base.py
pyqt_code_editor/mixins/check.py
pyqt_code_editor/mixins/comment.py
pyqt_code_editor/mixins/complete.py
pyqt_code_editor/mixins/execute.py
pyqt_code_editor/mixins/file_link.py
pyqt_code_editor/mixins/highlight_matching_brackets.py
pyqt_code_editor/mixins/line_number.py
pyqt_code_editor/mixins/merge_undo_actions.py
pyqt_code_editor/mixins/python_auto_indent.py
pyqt_code_editor/mixins/search_replace.py
pyqt_code_editor/mixins/shortcuts.py
pyqt_code_editor/mixins/smart_backspace_delete.py
pyqt_code_editor/mixins/symbols.py
pyqt_code_editor-0.0.55.dist-info/entry_points.txt
pyqt_code_editor-0.0.55.dist-info/licenses/COPYING
pyqt_code_editor-0.0.55.dist-info/WHEEL
pyqt_code_editor-0.0.55.dist-info/METADATA
pyqt_code_editor-0.0.55.dist-info/RECORD
