Metadata-Version: 2.4
Name: pyqt_code_editor
Version: 0.0.55
Summary: Fully featured code-editor widgets for PyQt
Keywords: code editor,pyqt,ide
Author-email: Sebastiaan Mathôt <s.mathot@cogsci.nl>
Requires-Python: >=3.10
License-File: COPYING
Requires-Dist: chardet
Requires-Dist: detect-indent
Requires-Dist: jedi
Requires-Dist: httpx<0.29.0
Requires-Dist: mistralai
Requires-Dist: opensesame-extension-sigmund
Requires-Dist: pathspec
Requires-Dist: psutil
Requires-Dist: pygments
Requires-Dist: qtawesome
Requires-Dist: qtpy
Requires-Dist: pyqt6
Requires-Dist: qtconsole
Requires-Dist: tree-sitter
Requires-Dist: tree-sitter-javascript
Requires-Dist: tree-sitter-json
Requires-Dist: tree-sitter-html
Requires-Dist: tree-sitter-python
Requires-Dist: tree-sitter-toml
Requires-Dist: tree-sitter-yaml
Requires-Dist: ruff
Project-URL: Source, https://github.com/open-cogsci/sigmund-analyst
